{
    "key": "group_64cdc46022cbc",
    "title": "Block : Experience",
    "fields": [
        {
            "key": "field_64cdc4608d221",
            "label": "Block : Experience",
            "name": "",
            "aria-label": "",
            "type": "accordion",
            "instructions": "",
            "required": 0,
            "conditional_logic": 0,
            "wrapper": {
                "width": "",
                "class": "",
                "id": ""
            },
            "show_in_graphql": 1,
            "open": 0,
            "multi_expand": 0,
            "endpoint": 0
        },
        {
            "key": "field_64cdd74183462",
            "label": "Section ID",
            "name": "section_id",
            "aria-label": "",
            "type": "text",
            "instructions": "",
            "required": 0,
            "conditional_logic": 0,
            "wrapper": {
                "width": "",
                "class": "",
                "id": ""
            },
            "show_in_graphql": 1,
            "default_value": "",
            "maxlength": "",
            "placeholder": "",
            "prepend": "",
            "append": ""
        },
        {
            "key": "field_64cdc4868d222",
            "label": "Title",
            "name": "title",
            "aria-label": "",
            "type": "text",
            "instructions": "",
            "required": 0,
            "conditional_logic": 0,
            "wrapper": {
                "width": "",
                "class": "",
                "id": ""
            },
            "show_in_graphql": 1,
            "default_value": "",
            "maxlength": "",
            "placeholder": "",
            "prepend": "",
            "append": ""
        },
        {
            "key": "field_64cdc49d8d223",
            "label": "Experience List",
            "name": "experience_list",
            "aria-label": "",
            "type": "repeater",
            "instructions": "",
            "required": 0,
            "conditional_logic": 0,
            "wrapper": {
                "width": "",
                "class": "",
                "id": ""
            },
            "show_in_graphql": 1,
            "layout": "block",
            "pagination": 0,
            "min": 0,
            "max": 0,
            "collapsed": "",
            "button_label": "Add Row",
            "rows_per_page": 20,
            "sub_fields": [
                {
                    "key": "field_64cdc5438d224",
                    "label": "Job Title",
                    "name": "job_title",
                    "aria-label": "",
                    "type": "text",
                    "instructions": "",
                    "required": 0,
                    "conditional_logic": 0,
                    "wrapper": {
                        "width": "",
                        "class": "",
                        "id": ""
                    },
                    "show_in_graphql": 1,
                    "default_value": "",
                    "maxlength": "",
                    "placeholder": "",
                    "prepend": "",
                    "append": "",
                    "parent_repeater": "field_64cdc49d8d223"
                },
                {
                    "key": "field_64cde362e307e",
                    "label": "Other Designations",
                    "name": "other_designations",
                    "aria-label": "",
                    "type": "repeater",
                    "instructions": "",
                    "required": 0,
                    "conditional_logic": 0,
                    "wrapper": {
                        "width": "",
                        "class": "",
                        "id": ""
                    },
                    "show_in_graphql": 1,
                    "layout": "block",
                    "pagination": 0,
                    "min": 0,
                    "max": 0,
                    "collapsed": "",
                    "button_label": "Add Row",
                    "rows_per_page": 20,
                    "sub_fields": [
                        {
                            "key": "field_64cde3c5e307f",
                            "label": "Designation",
                            "name": "designation",
                            "aria-label": "",
                            "type": "text",
                            "instructions": "",
                            "required": 0,
                            "conditional_logic": 0,
                            "wrapper": {
                                "width": "",
                                "class": "",
                                "id": ""
                            },
                            "show_in_graphql": 1,
                            "default_value": "",
                            "maxlength": "",
                            "placeholder": "",
                            "prepend": "",
                            "append": "",
                            "parent_repeater": "field_64cde362e307e"
                        }
                    ],
                    "parent_repeater": "field_64cdc49d8d223"
                },
                {
                    "key": "field_64cdc9e88d225",
                    "label": "Organization",
                    "name": "organization",
                    "aria-label": "",
                    "type": "link",
                    "instructions": "",
                    "required": 0,
                    "conditional_logic": 0,
                    "wrapper": {
                        "width": "",
                        "class": "",
                        "id": ""
                    },
                    "show_in_graphql": 1,
                    "return_format": "array",
                    "parent_repeater": "field_64cdc49d8d223"
                },
                {
                    "key": "field_64cdcabf8d227",
                    "label": "Duration",
                    "name": "duration",
                    "aria-label": "",
                    "type": "text",
                    "instructions": "",
                    "required": 0,
                    "conditional_logic": 0,
                    "wrapper": {
                        "width": "",
                        "class": "",
                        "id": ""
                    },
                    "show_in_graphql": 1,
                    "default_value": "",
                    "maxlength": "",
                    "placeholder": "",
                    "prepend": "",
                    "append": "",
                    "parent_repeater": "field_64cdc49d8d223"
                },
                {
                    "key": "field_64cdca7f8d226",
                    "label": "Description",
                    "name": "description",
                    "aria-label": "",
                    "type": "wysiwyg",
                    "instructions": "",
                    "required": 0,
                    "conditional_logic": 0,
                    "wrapper": {
                        "width": "",
                        "class": "",
                        "id": ""
                    },
                    "show_in_graphql": 1,
                    "default_value": "",
                    "tabs": "all",
                    "toolbar": "full",
                    "media_upload": 1,
                    "delay": 0,
                    "parent_repeater": "field_64cdc49d8d223"
                }
            ]
        },
        {
            "key": "field_64cde89bccb76",
            "label": "Resume",
            "name": "resume",
            "aria-label": "",
            "type": "file",
            "instructions": "",
            "required": 0,
            "conditional_logic": 0,
            "wrapper": {
                "width": "",
                "class": "",
                "id": ""
            },
            "show_in_graphql": 1,
            "return_format": "array",
            "library": "all",
            "min_size": "",
            "max_size": "",
            "mime_types": ""
        }
    ],
    "location": [
        [
            {
                "param": "block",
                "operator": "==",
                "value": "acf\/sanyog-experience"
            }
        ]
    ],
    "menu_order": 0,
    "position": "normal",
    "style": "default",
    "label_placement": "top",
    "instruction_placement": "label",
    "hide_on_screen": "",
    "active": true,
    "description": "",
    "show_in_rest": 0,
    "show_in_graphql": 0,
    "graphql_field_name": "block:Experience",
    "map_graphql_types_from_location_rules": 0,
    "graphql_types": "",
    "modified": 1701540604
}
